aliusmangondalfinal3/__init__.py
aliusmangondalfinal3/add.py
aliusmangondalfinal3/subtract.py
aliusmangondalfinal3-0.0.1.dist-info/METADATA
aliusmangondalfinal3-0.0.1.dist-info/WHEEL
aliusmangondalfinal3-0.0.1.dist-info/top_level.txt
aliusmangondalfinal3-0.0.1.dist-info/RECORD
